odoo/addons/shopinvader_cart_expiry/README.rst
odoo/addons/shopinvader_cart_expiry/__init__.py
odoo/addons/shopinvader_cart_expiry/__manifest__.py
odoo/addons/shopinvader_cart_expiry/data/ir_cron.xml
odoo/addons/shopinvader_cart_expiry/data/queue_job_function_data.xml
odoo/addons/shopinvader_cart_expiry/i18n/shopinvader_cart_expiry.pot
odoo/addons/shopinvader_cart_expiry/migrations/14.0.1.0.1/post-migrate.py
odoo/addons/shopinvader_cart_expiry/models/__init__.py
odoo/addons/shopinvader_cart_expiry/models/sale_order.py
odoo/addons/shopinvader_cart_expiry/models/shopinvader_backend.py
odoo/addons/shopinvader_cart_expiry/readme/CONTRIBUTORS.rst
odoo/addons/shopinvader_cart_expiry/readme/DESCRIPTION.rst
odoo/addons/shopinvader_cart_expiry/services/__init__.py
odoo/addons/shopinvader_cart_expiry/services/abstract_sale.py
odoo/addons/shopinvader_cart_expiry/static/description/index.html
odoo/addons/shopinvader_cart_expiry/tests/__init__.py
odoo/addons/shopinvader_cart_expiry/tests/test_cart_expiry.py
odoo/addons/shopinvader_cart_expiry/views/shopinvader_backend.xml
odoo14_addon_shopinvader_cart_expiry-14.0.1.0.2.dist-info/METADATA
odoo14_addon_shopinvader_cart_expiry-14.0.1.0.2.dist-info/WHEEL
odoo14_addon_shopinvader_cart_expiry-14.0.1.0.2.dist-info/top_level.txt
odoo14_addon_shopinvader_cart_expiry-14.0.1.0.2.dist-info/RECORD
